LICENSE.txt
MANIFEST.in
requirements.txt
setup.cfg
setup.py
github_pull_request/__init__.py
github_pull_request/cli.py
github_pull_request/pr.py
github_pull_request/utils.py
github_pull_request.egg-info/PKG-INFO
github_pull_request.egg-info/SOURCES.txt
github_pull_request.egg-info/dependency_links.txt
github_pull_request.egg-info/entry_points.txt
github_pull_request.egg-info/not-zip-safe
github_pull_request.egg-info/requires.txt
github_pull_request.egg-info/top_level.txt