Metadata-Version: 1.1
Name: github-pull-request
Version: 0.0.5
Summary: CLI tool to manage GitHub PRs
Home-page: https://github.com/lolatravel/github-pull-request
Author: Kevin LaFlamme
Author-email: kevin@lola.com
License: MIT
Platform: any
Classifier: Development Status :: 4 - Beta
Classifier: Environment :: Console
Classifier: Intended Audience :: Developers
Classifier: License :: OSI Approved :: BSD License
Classifier: Operating System :: POSIX
Classifier: Operating System :: MacOS
Classifier: Operating System :: Unix
Classifier: Operating System :: Microsoft :: Windows
Classifier: Programming Language :: Python
Classifier: Programming Language :: Python :: 2
Classifier: Programming Language :: Python :: 3
Classifier: Topic :: Software Development :: Libraries :: Python Modules
